django_timelines-0.3.dist-info/DESCRIPTION.rst
django_timelines-0.3.dist-info/METADATA
django_timelines-0.3.dist-info/RECORD
django_timelines-0.3.dist-info/WHEEL
django_timelines-0.3.dist-info/metadata.json
django_timelines-0.3.dist-info/top_level.txt
example/media/__init__.py
example/media/adapters.py
example/media/admin.py
example/media/models.py
example/media/urls/__init__.py
example/media/urls/photos.py
example/media/urls/videos.py
example/simpleapp/__init__.py
example/simpleapp/admin.py
example/simpleapp/models.py
example/simpleapp/urls.py
timelines/__init__.py
timelines/admin.py
timelines/apps.py
timelines/fields.py
timelines/models.py
timelines/old-initial.py
timelines/registration.py
timelines/settings.py
timelines/tests.py
timelines/urls.py
timelines/views.py
timelines/migrations/0001_initial.py
timelines/migrations/0002_misc_model_tweaks.py
timelines/migrations/0003_add_concepts.py
timelines/migrations/0004_add_credits.py
timelines/migrations/__init__.py
timelines/static/.DS_Store
timelines/static/timelines/jscolor.js
timelines/static/timelines/jscolor.min.js
timelines/static/timelines/timeline_admin.js
timelines/templates/timelines/base.html
timelines/templates/timelines/color.html
timelines/templates/timelines/timeline_detail.html
timelines/templatetags/__init__.py
timelines/templatetags/timeline_tags.py
