Metadata-Version: 2.0
Name: django-timelines
Version: 0.3
Summary: timeline
Home-page: https://github.com/Natgeoed/django-timelines
Author: Corey Oordt
Author-email: coreyoordt@gmail.com
License: UNKNOWN
Platform: UNKNOWN
Classifier: Framework :: Django
Requires-Dist: django-ckeditor
Requires-Dist: django-concepts
Requires-Dist: django-contentrelations
Requires-Dist: swapper
